wizsearch/__init__.py
wizsearch/base.py
wizsearch/page_crawler.py
wizsearch/wizsearch.py
wizsearch/engines/baidu_search.py
wizsearch/engines/base_tarzi_search.py
wizsearch/engines/bing_search.py
wizsearch/engines/brave_search.py
wizsearch/engines/duckduckgo_search.py
wizsearch/engines/google_ai_search.py
wizsearch/engines/google_search.py
wizsearch/engines/searxng_search.py
wizsearch/engines/tavily_search.py
wizsearch/engines/wechat_search.py
wizsearch/semsearch/__init__.py
wizsearch/semsearch/docproc.py
wizsearch/semsearch/models.py
wizsearch/semsearch/semantic_search.py
wizsearch-1.1.dist-info/licenses/LICENSE
wizsearch-1.1.dist-info/METADATA
wizsearch-1.1.dist-info/WHEEL
wizsearch-1.1.dist-info/top_level.txt
wizsearch-1.1.dist-info/RECORD
